.travis.yml
AUTHORS
CODE_OF_CONDUCT.md
ChangeLog
LICENSE
README.md
appveyor.yml
codecov.yml
requirements.txt
setup.cfg
setup.py
tox.ini
wexpect.py
.github/ISSUE_TEMPLATE/bug_report.md
.github/ISSUE_TEMPLATE/feature_request.md
examples/README.md
examples/cmd_wrapper.py
examples/foo.py
examples/hello_wexpect.py
examples/python.py
issues/README.md
issues/bla.py
issues/bla2.py
issues/i09_cmd_error.py
issues/i09_py_sim_no_error.py
issues/i09_py_sim_no_error2.py
issues/i10_parent.py
issues/i11_greek_parent.py
issues/i11_greek_printer.py
issues/i11_unicode_parent.py
issues/i11_unicode_printer.py
issues/long_printer.py
tests/PexpectTestCase.py
tests/__init__.py
tests/foo.py
tests/lines_printer.py
tests/test_command_list_split.py
tests/test_constructor.py
tests/test_delay.py
tests/test_destructor.py
tests/test_echo.py
tests/test_interact.py
tests/test_readline.py
wexpect.egg-info/PKG-INFO
wexpect.egg-info/SOURCES.txt
wexpect.egg-info/dependency_links.txt
wexpect.egg-info/not-zip-safe
wexpect.egg-info/pbr.json
wexpect.egg-info/requires.txt
wexpect.egg-info/top_level.txt